bagel/__init__.py
bagel/config.py
bagel/errors.py
bagel/api/Cluster.py
bagel/api/__init__.py
bagel/api/fastapi.py
bagel/api/types.py
bagel/utils/__init__.py
test/__init__.py
test/client_test.py
test/opt_test.py
betabageldb-0.2.45.dist-info/METADATA
betabageldb-0.2.45.dist-info/WHEEL
betabageldb-0.2.45.dist-info/top_level.txt
betabageldb-0.2.45.dist-info/RECORD
