Metadata-Version: 2.1
Name: betabageldb
Version: 0.2.45
Summary: BagelDB is a Python library for interacting with the BagelDB API.
Home-page: https://github.com/Bagel-DB/Client
Author: Bidhan Roy
Author-email: bidhan@bageldb.ai
Classifier: Development Status :: 3 - Alpha
Classifier: Intended Audience :: Developers
Classifier: Programming Language :: Python :: 3
Classifier: Programming Language :: Python :: 3.7
Classifier: Programming Language :: Python :: 3.8
Classifier: Programming Language :: Python :: 3.9
Requires-Dist: certifi >=2023.5.7
Requires-Dist: charset-normalizer >=3.2.0
Requires-Dist: graphlib-backport >=1.0.3
Requires-Dist: idna >=3.4
Requires-Dist: numpy >=1.21.6
Requires-Dist: overrides >=7.3.1
Requires-Dist: pandas >=2.0.1
Requires-Dist: pydantic <2.0,>=1.10.10
Requires-Dist: python-dateutil >=2.8.2
Requires-Dist: pytz >=2023.3
Requires-Dist: requests >=2.28
Requires-Dist: six >=1.16.0
Requires-Dist: typing-extensions >=4.6.3
Requires-Dist: urllib3 >=1.26.16
Requires-Dist: tzdata >=2022.1
